{
  "tags":{
    "测试": "cyan",
    "理解": "red",
    "发电": "cyan"
  },

  "tags_colors": [
    "red",
    "yellow",
    "green",
    "blue",
    "purple",
    "cyan",
    "不要更改此处！"
  ],

  "hub_items": [
    {
      "title": "测试",
      "image": "blank.png",
      "description": "测试",
      "tags": ["测试"]
    },
    {
      "title": "悲伤香蕉1.0",
      "image": "悲伤香蕉1.0.png",
      "description": "可怜的单身香蕉",
      "tags": ["理解"]
    },
    {
      "title": "悲伤香蕉2.0",
      "image": "悲伤香蕉2.0.png",
      "description": "张老师珍贵手稿首次公布！",
      "tags": ["理解","发电"]
    },
    {
      "title": "史诗般的行走",
      "image": "史诗般的行走.png",
      "description": "粟教最新教义，必须理解",
      "tags": ["理解","发电"]
    }
  ]
}
